etcd/__init__.py
etcd/auth.py
etcd/client.py
etcd/lock.py
etcd/tests/__init__.py
etcd/tests/test_auth.py
etcd/tests/integration/__init__.py
etcd/tests/integration/helpers.py
etcd/tests/integration/test_simple.py
etcd/tests/integration/test_ssl.py
etcd/tests/unit/__init__.py
etcd/tests/unit/test_client.py
etcd/tests/unit/test_lock.py
etcd/tests/unit/test_old_request.py
etcd/tests/unit/test_request.py
etcd/tests/unit/test_result.py
jb_python_etcd-0.1.3.dist-info/DESCRIPTION.rst
jb_python_etcd-0.1.3.dist-info/METADATA
jb_python_etcd-0.1.3.dist-info/RECORD
jb_python_etcd-0.1.3.dist-info/WHEEL
jb_python_etcd-0.1.3.dist-info/metadata.json
jb_python_etcd-0.1.3.dist-info/top_level.txt
